[
    {
        "shippingAddress": {
            "street": "agsagasg",
            "number": "12",
            "zipCode": "12345",
            "city": "lishdhlsd"
        },
        "_id": "67f7babc64ea98b4159440cd",
        "email": "user@user.com",
        "firstname": "User",
        "lastname": "Nilss",
        "phonenumber": "0760171007",
        "orderItem": [
            {
                "productId": "67efaaa8202faa3dbb38ec01",
                "quantity": 5,
                "_id": "67f7babc64ea98b4159440ce"
            },
            {
                "productId": "67efaaa8202faa3dbb38ec02",
                "quantity": 4,
                "_id": "67f7babc64ea98b4159440cf"
            }
        ]
    },
    {
        "shippingAddress": {
            "street": "Zzmm",
            "number": "Bbb",
            "zipCode": "12345",
            "city": "Th"
        },
        "_id": "67f7bb7f64ea98b4159442dd",
        "email": "admin@admin.com",
        "firstname": "Admin",
        "lastname": "Nsns",
        "phonenumber": "0728218212",
        "orderItem": [
            {
                "productId": "67efaaa8202faa3dbb38ec01",
                "quantity": 1,
                "_id": "67f7bb7f64ea98b4159442de"
            }
        ]
    },
    {
        "shippingAddress": {
            "street": "gatan",
            "number": "32",
            "zipCode": "12345",
            "city": "malmö"
        },
        "_id": "67f7bb8564ea98b4159442e1",
        "email": "fsad@fdas.se",
        "firstname": "Oztesttttt",
        "lastname": "ALbayrak",
        "phonenumber": "0112345676",
        "orderItem": [
            {
                "productId": "67efaaa8202faa3dbb38ec09",
                "quantity": 1,
                "_id": "67f7bb8564ea98b4159442e2"
            },
            {
                "productId": "67efaaa8202faa3dbb38ec08",
                "quantity": 1,
                "_id": "67f7bb8564ea98b4159442e3"
            },
            {
                "productId": "67efaaa8202faa3dbb38ec0a",
                "quantity": 2,
                "_id": "67f7bb8564ea98b4159442e4"
            },
            {
                "productId": "67efaaa8202faa3dbb38ec0c",
                "quantity": 4,
                "_id": "67f7bb8564ea98b4159442e5"
            }
        ]
    },
    {
        "shippingAddress": {
            "street": "Bäverbäcksgränd",
            "number": "1234567",
            "zipCode": "21212",
            "city": "Kiruna"
        },
        "_id": "67f7bbb4e667f199e1c80f2f",
        "email": "user@user.com",
        "firstname": "Mulle",
        "lastname": "Meck",
        "phonenumber": "0542134521",
        "orderItem": [
            {
                "productId": "67efaaa8202faa3dbb38ec05",
                "quantity": 3,
                "_id": "67f7bbb4e667f199e1c80f30"
            },
            {
                "productId": "67efaaa8202faa3dbb38ec06",
                "quantity": 3,
                "_id": "67f7bbb4e667f199e1c80f31"
            },
            {
                "productId": "67efaaa8202faa3dbb38ec0a",
                "quantity": 2,
                "_id": "67f7bbb4e667f199e1c80f32"
            }
        ]
    }
]
